aicippy/__init__.py
aicippy/config.py
aicippy/exceptions.py
aicippy/py.typed
aicippy/types.py
aicippy/agents/__init__.py
aicippy/agents/models.py
aicippy/agents/orchestrator.py
aicippy/agents/status.py
aicippy/agents/usage.py
aicippy/auth/__init__.py
aicippy/auth/cognito.py
aicippy/auth/keychain.py
aicippy/auth/models.py
aicippy/cli/__init__.py
aicippy/cli/ai_command_executor.py
aicippy/cli/human_verify.py
aicippy/cli/interactive.py
aicippy/cli/main.py
aicippy/cli/mascot.py
aicippy/cli/shell_executor.py
aicippy/cli/ui_components.py
aicippy/cli/upload_manager.py
aicippy/connectors/__init__.py
aicippy/connectors/aws.py
aicippy/connectors/base.py
aicippy/connectors/firebase.py
aicippy/connectors/github.py
aicippy/connectors/registry.py
aicippy/connectors/shell.py
aicippy/installer/__init__.py
aicippy/installer/dependency_manager.py
aicippy/installer/env_manager.py
aicippy/installer/main.py
aicippy/installer/permission_manager.py
aicippy/installer/platform_detect.py
aicippy/installer/progress_ui.py
aicippy/installer/session_manager.py
aicippy/knowledge/__init__.py
aicippy/knowledge/crawler.py
aicippy/knowledge/indexer.py
aicippy/knowledge/project_scanner.py
aicippy/knowledge/summarizer.py
aicippy/notifications/__init__.py
aicippy/notifications/email.py
aicippy/utils/__init__.py
aicippy/utils/correlation.py
aicippy/utils/logging.py
aicippy/utils/retry.py
aicippy/websocket/__init__.py
aicippy/websocket/client.py
aicippy/websocket/models.py
aicippy/websocket/realtime.py
aicippy-1.0.9.dist-info/METADATA
aicippy-1.0.9.dist-info/WHEEL
aicippy-1.0.9.dist-info/entry_points.txt
aicippy-1.0.9.dist-info/RECORD
