Metadata-Version: 2.4
Name: aicippy
Version: 1.0.9
Summary: Enterprise-grade multi-agent CLI system powered by AWS Bedrock
Project-URL: Homepage, https://aicippy.io
Project-URL: Documentation, https://docs.aicippy.io
Project-URL: Repository, https://github.com/aivibe/aicippy
Project-URL: Issues, https://github.com/aivibe/aicippy/issues
Author-email: Aravind Jayamohan <aravind@aivibe.in>
Maintainer-email: AiVibe Software Services Pvt Ltd <support@aivibe.in>
License: Proprietary
Keywords: ai,aws,bedrock,cli,enterprise,multi-agent
Classifier: Development Status :: 5 - Production/Stable
Classifier: Environment :: Console
Classifier: Intended Audience :: Developers
Classifier: License :: Other/Proprietary License
Classifier: Operating System :: OS Independent
Classifier: Programming Language :: Python :: 3
Classifier: Programming Language :: Python :: 3.11
Classifier: Programming Language :: Python :: 3.12
Classifier: Programming Language :: Python :: 3.13
Classifier: Programming Language :: Python :: 3.14
Classifier: Topic :: Software Development :: Libraries :: Python Modules
Classifier: Topic :: System :: Shells
Classifier: Typing :: Typed
Requires-Python: >=3.11
Requires-Dist: aiofiles>=23.2.0
Requires-Dist: anyio>=4.3.0
Requires-Dist: beautifulsoup4>=4.12.0
Requires-Dist: boto3>=1.34.0
Requires-Dist: botocore>=1.34.0
Requires-Dist: feedparser>=6.0.11
Requires-Dist: httpx>=0.27.0
Requires-Dist: keyring>=25.0.0
Requires-Dist: lxml>=5.1.0
Requires-Dist: markdown>=3.5.0
Requires-Dist: orjson>=3.9.0
Requires-Dist: prompt-toolkit>=3.0.43
Requires-Dist: pydantic-settings>=2.2.0
Requires-Dist: pydantic>=2.6.0
Requires-Dist: python-jose[cryptography]>=3.3.0
Requires-Dist: rich>=13.7.0
Requires-Dist: structlog>=24.1.0
Requires-Dist: tenacity>=8.2.0
Requires-Dist: typer>=0.12.0
Requires-Dist: websockets>=12.0
Provides-Extra: cdk
Requires-Dist: aws-cdk-lib>=2.130.0; extra == 'cdk'
Requires-Dist: constructs>=10.3.0; extra == 'cdk'
Provides-Extra: dev
Requires-Dist: black>=24.1.0; extra == 'dev'
Requires-Dist: boto3-stubs[essential]>=1.34.0; extra == 'dev'
Requires-Dist: moto[all]>=5.0.0; extra == 'dev'
Requires-Dist: mypy>=1.8.0; extra == 'dev'
Requires-Dist: pre-commit>=3.6.0; extra == 'dev'
Requires-Dist: pytest-asyncio>=0.23.0; extra == 'dev'
Requires-Dist: pytest-cov>=4.1.0; extra == 'dev'
Requires-Dist: pytest-mock>=3.12.0; extra == 'dev'
Requires-Dist: pytest>=8.0.0; extra == 'dev'
Requires-Dist: ruff>=0.2.0; extra == 'dev'
